{
  "web": {
    "client_id": "739612828231-qu956bv1d3f2i17d4rnmsgf002cqc7e7.apps.googleusercontent.com",
    "project_id": "disco-history-163915",
    "auth_uri": "https:\/\/accounts.google.com\/o\/oauth2\/auth",
    "token_uri": "https:\/\/accounts.google.com\/o\/oauth2\/token",
    "auth_provider_x509_cert_url": "https:\/\/www.googleapis.com\/oauth2\/v1\/certs",
    "client_secret": "rdlvoJUZMBBj3RuI_Wyb-39a",
    "javascript_origins": [
      "http:\/\/localhost:8080\/authGoogleDrive",
      "http:\/\/localhost:8080"
    ]
  }
}